poisson_glm_diss/PoissonGLM.py
poisson_glm_diss/__init__.py
poisson_glm_diss-1.0.0.dist-info/METADATA
poisson_glm_diss-1.0.0.dist-info/WHEEL
poisson_glm_diss-1.0.0.dist-info/top_level.txt
poisson_glm_diss-1.0.0.dist-info/RECORD
