Metadata-Version: 2.1
Name: poisson_glm_diss
Version: 1.0.0
Summary: A small package for Poisson GLM functionality
Home-page: https://github.com/cameronkent1
Author: Cameron Kent
Author-email: cameron.kent@hotmail.co.uk
Classifier: Programming Language :: Python :: 3
Classifier: License :: OSI Approved :: MIT License
Classifier: Operating System :: OS Independent
